{
  "id": "wax-play-she-on-him",
  "slug": "wax-play-she-on-him",
  "version": 2,
  "scene_type": "clarification",
  "clarification_for": [
    "rough",
    "romantic"
  ],
  "is_active": true,
  "is_onboarding": false,
  "for_gender": "female",
  "paired_scene": "wax-play-f-to-m-receive",
  "role_direction": "f_to_m",
  "title": {
    "ru": "Восковые игры",
    "en": "Wax Play"
  },
  "subtitle": {
    "ru": "Она капает на него",
    "en": "She drips on him"
  },
  "user_description": {
    "ru": "Ты капаешь горячий воск свечи на его тело.",
    "en": "You drip hot candle wax on his body."
  },
  "ai_description": {
    "ru": "Он лежит связанный, она стоит над ним со свечой. Медленно наклоняет — капля горячего воска падает на его грудь. Он дёргается, но не может двигаться.",
    "en": "He lies bound, she stands over him with a candle. Slowly tilts it — a drop of hot wax falls on his chest. He jerks, but cannot move."
  },
  "image_prompt": "woman dripping candle wax on mans chest, he nude lying on bed, she in lingerie holding candle above, red wax drops visible, bedroom setting, candlelit",
  "intensity": 3,
  "category": "impact-pain",
  "tags": [
    "wax_play",
    "femdom",
    "temperature_play",
    "sensory",
    "male_submission"
  ],
  "ai_context": {
    "tests_primary": [
      "wax_play",
      "femdom",
      "temperature_play"
    ],
    "tests_secondary": [
      "male_submission",
      "pain_pleasure",
      "sensory"
    ],
    "emotional_range": {
      "positive": [
        "enjoys femdom",
        "pain-pleasure connection",
        "submissive"
      ],
      "negative": [
        "fear of burns",
        "not into pain",
        "prefers control"
      ]
    }
  },
  "question": {
    "type": "swipe",
    "text": {
      "ru": "Что привлекает когда она капает воск?",
      "en": "What appeals about her dripping wax?"
    }
      }
}
